uv_run_module/__init__.py
uv_run_module/__main__.py
uv_run_module-0.1.0.dist-info/licenses/LICENSE
uv_run_module-0.1.0.dist-info/METADATA
uv_run_module-0.1.0.dist-info/WHEEL
uv_run_module-0.1.0.dist-info/entry_points.txt
uv_run_module-0.1.0.dist-info/top_level.txt
uv_run_module-0.1.0.dist-info/RECORD
