Metadata-Version: 2.4
Name: uv-run-module
Version: 0.1.0
Summary: Tiny launcher that cd's into a project and runs your command via Astral uv (or uvx) without modifying it.
Author-email: Joao Carvalho <joao@limacarvalho.com>
License:                     GNU GENERAL PUBLIC LICENSE
Project-URL: Homepage, https://github.com/limacarvalho/uv-run-module
Project-URL: Repository, https://github.com/limacarvalho/uv-run-module.git
Keywords: uv,uvx,launcher,cli,kubernetes,streamlit,flask,uvicorn
Classifier: Programming Language :: Python :: 3
Classifier: License :: OSI Approved :: GNU General Public License v3 or later (GPLv3+)
Classifier: Environment :: Console
Classifier: Operating System :: OS Independent
Requires-Python: >=3.9
License-File: LICENSE
Dynamic: license-file
